sphinx_tippy.py
sphinx_tippy-0.4.3.dist-info/LICENSE
sphinx_tippy-0.4.3.dist-info/WHEEL
sphinx_tippy-0.4.3.dist-info/METADATA
sphinx_tippy-0.4.3.dist-info/RECORD
